{"data": {"viewer": {"user": null}, "node": {"__typename": "Application", "__isAppStoreItem": "Application", "id": "2223615721048141", "display_name": "Vader Immortal: Episode II", "platform": "ANDROID_6DOF", "iarc_cert": {"iarc_rating": {"descriptors": ["血腥", "暴力内容"], "interactive_elements": [], "id": "1911256448977149", "large_age_rating_image": {"uri": "https://scontent.oculuscdn.com/v/t64.5771-25/12138850_239447016475616_966858255714222080_n.png?_nc_cat=1&ccb=2&_nc_sid=79b88e&_nc_ohc=5br7VDqk_f0AX_gOkjL&_nc_ht=scontent.oculuscdn.com&oh=84a73de4f0e90bf3230ff3d8a9faf05c&oe=60129719"}, "small_age_rating_image": {"uri": "https://scontent.oculuscdn.com/v/t64.5771-25/12138850_1786874088228955_5598594603113512960_n.png?_nc_cat=1&ccb=2&_nc_sid=79b88e&_nc_ohc=zddTCFVaBDcAX_wBEiG&_nc_ht=scontent.oculuscdn.com&oh=0fdb553fceee8b9c135da69839d0464c&oe=6011D8C2"}, "age_rating_text": "Teen", "rating_definition_uri": "https://www.globalratings.com/ratings-guide-esrb", "__typename": "IARCRating"}, "id": "1911256435643817"}, "category": "ENTERTAINMENT", "item_bundles": [], "__isWithHeroMediaCarousel": "Application", "hero": {"uri": "https://scontent.oculuscdn.com/v/t64.5771-25/q92/s2048x2048/38982596_751060558688488_8715039301341020160_n.jpg?_nc_cat=100&ccb=2&_nc_sid=79b88e&_nc_ohc=uFfTxWrMgXIAX8MYJG4&_nc_ht=scontent.oculuscdn.com&tp=28&oh=2f353065d6fff6b51f327dae46a65398&oe=60103FB2"}, "screenshots": [{"uri": "https://scontent.oculuscdn.com/v/t64.5771-25/q92/s1440x1440/38982595_533022753908276_3875450923639635968_n.jpg?_nc_cat=105&ccb=2&_nc_sid=79b88e&_nc_ohc=UzayANEQCLcAX_JdT0M&_nc_ht=scontent.oculuscdn.com&tp=28&oh=64bd7f23ac16aa4d65c0d819fc397f4f&oe=6011F898"}, {"uri": "https://scontent.oculuscdn.com/v/t64.5771-25/q92/s1440x1440/38982667_1663645827101639_4194141246509285376_n.jpg?_nc_cat=110&ccb=2&_nc_sid=79b88e&_nc_ohc=JkAEpLgKb30AX_6zI-D&_nc_ht=scontent.oculuscdn.com&tp=28&oh=042b0d28d4485d005b1b8edbbf084c35&oe=6010F4CD"}, {"uri": "https://scontent.oculuscdn.com/v/t64.5771-25/q92/s1440x1440/38974664_1608999335900769_1528960481375551488_n.jpg?_nc_cat=110&ccb=2&_nc_sid=79b88e&_nc_ohc=PLEkZu7kWM0AX8-qupZ&_nc_ht=scontent.oculuscdn.com&tp=28&oh=6e03d0c9e76595b81173082b925b09a4&oe=60126292"}, {"uri": "https://scontent.oculuscdn.com/v/t64.5771-25/q92/s1440x1440/38982609_2393176247629718_886116066005090304_n.jpg?_nc_cat=100&ccb=2&_nc_sid=79b88e&_nc_ohc=vIxgJut2W3EAX-zqyX4&_nc_ht=scontent.oculuscdn.com&tp=28&oh=ee43bea3a59237c072ed27b99c5280da&oe=60113FEA"}, {"uri": "https://scontent.oculuscdn.com/v/t64.5771-25/q92/s1440x1440/38974499_680053465840285_304451101829103616_n.jpg?_nc_cat=110&ccb=2&_nc_sid=79b88e&_nc_ohc=0tfzLfEPoRsAX8vpswA&_nc_ht=scontent.oculuscdn.com&tp=28&oh=1ceab4e23f7660ee2446531ed4c3b740&oe=60127F33"}], "trailer": {"thumbnail": {"uri": "https://scontent.oculuscdn.com/v/t64.5771-25/q92/s1440x1440/39031429_2363243137264976_4833346652053962752_n.jpg?_nc_cat=109&ccb=2&_nc_sid=79b88e&_nc_ohc=c1Ila94aw7gAX_7RLQk&_nc_ht=scontent.oculuscdn.com&tp=28&oh=03cb5af115f2d728aee9bf872c1ee70b&oe=60128FAE"}, "uri": "https://scontent.oculuscdn.com/v/t64.7195-25/10000000_2363242410598382_5688859053145456640_n.mp4?_nc_cat=109&ccb=2&_nc_sid=0ed769&_nc_ohc=-l9Pob4FxoUAX8A0ohX&_nc_ht=scontent.oculuscdn.com&oh=c575b326e8b9a23965bfc6cd6430d064&oe=6010245B"}, "quality_rating_histogram_aggregate_all": [{"star_rating": 1, "count": 161, "starRating": 1}, {"star_rating": 2, "count": 215, "starRating": 2}, {"star_rating": 3, "count": 458, "starRating": 3}, {"star_rating": 4, "count": 756, "starRating": 4}, {"star_rating": 5, "count": 2017, "starRating": 5}], "display_long_description": "Continue your journey into the heart of Darth Vader's dark fortress in Vader Immortal: A Star Wars VR Series - Episode II. With the fearsome Sith Lord as your guide, you'll perfect your lightsaber skills against terrifying new enemies, and master the Force as you discover the truth of an ancient mystery beneath the fiery surface of Mustafar. Starring Maya Rudolph, Vader Immortal is a canonical Star Wars experience created by ILMxLAB and Lucasfilm in collaboration with Oculus Studios.", "developer_privacy_policy_url": "https://privacy.thewaltdisneycompany.com/", "developer_terms_of_service_url": "https://disneytermsofuse.com/", "supported_player_modes": ["SITTING", "STANDING", "ROOM_SCALE"], "publisher_name": "Disney Electronic Content, Inc.", "supported_in_app_languages": [{"name": "德语"}, {"name": "意大利语"}, {"name": "日语"}, {"name": "法语（法国）"}, {"name": "英语"}, {"name": "西班牙语（墨西哥）"}, {"name": "韩语"}], "supported_hmd_platforms": ["MONTEREY"], "supported_input_device_names": ["Oculus Touch"], "user_interaction_mode_names": ["单人"], "age_rating": null, "category_name": "娱乐", "developer_name": "ILMxLAB", "genre_names": ["动作", "电影", "故事"], "is_360_sensor_setup_required": false, "is_concept": false, "latest_supported_binary": {"__typename": "AndroidBinary", "version": "2.0.2", "change_log": "- Implemented French, German, Japanese, Korean, Italian, and Spanish subtitles and menus\n- Fixes to increase stability in the Lady Corvax pinboard hallway\n- Fixed an issue that could lead to a long black screen at startup after an OS update", "supported_hmd_types": ["MONTEREY"], "total_installed_space": "3879130885", "id": "2829902237086150", "required_space_adjusted": "7548360469", "storeAddOns": null, "firstIapItems": null}, "recommended_graphics": null, "recommended_memory_gb": null, "recommended_processor": null, "release_date": 1569436136, "supported_tracking_modes": [], "website_url": "https://www.ilmxlab.com/", "current_offer": {"__typename": "AppStoreOffer", "offer_type": "APPSTORE_OFFER", "id": "427726621439563", "__isPurchasableOfferWithApp": "AppStoreOffer", "price": {"currency": "USD", "offset_amount": "999", "formatted": "US$ 9.99"}, "strikethrough_price": null, "promo_benefit": null, "end_time": 0, "show_timer": false, "buy_button_captions": []}, "viewer_release_channel": {"id": "455644904979306"}, "live_release_channel": {"id": "455644904979306", "channel_name": "LIVE", "latest_supported_binary": {"__typename": "AndroidBinary", "id": "2829902237086150"}}, "release_channels": {"count": 1, "nodes": [{"channel_name": "LIVE", "id": "455644904979306", "latest_supported_binary": {"__typename": "AndroidBinary", "version": "2.0.2", "id": "2829902237086150"}}]}, "grouping": {"upcoming_events": {"edges": []}, "id": "410958959456770", "posts": {"nodes": []}, "iap_items_2": {"edges": []}}, "externalReviewsForDisplay": {"nodes": []}, "externalReviewsComplete": {"count": 0}, "user_data_disclosure_translated": null, "__isItemWithComfortRating": "Application", "comfort_rating": "COMFORTABLE_FOR_MOST", "is_viewer_subscribed_coming_soon": false, "internet_connection": "NOT_REQUIRED", "internet_connection_name": "无需联网", "__isItemWithHmdPlatformInformaton": "Application", "supported_input_devices_list": [{"name": "Oculus Touch", "tag": "OCULUS_TOUCH"}], "canonicalName": "ilmxlab-vader-immortal-episode-ii-android6d0f", "viewer_has_preorder": false, "purchase_alerts": [], "is_granted_on_hardware_registration": false, "current_trial_offer": null, "extra_buy_box_section": {"content": "Oculus 退款政策", "link_uri": "https://www.oculus.com/legal/quest-rift-content-refund-policy/"}, "is_viewer_entitled": false, "baseline_offer": {"price": {"offset_amount": "999"}, "id": "427726621439563"}, "__isWishlistableItem": "Application", "entry": null, "is_demo_of": null, "appName": "Vader Immortal: Episode II", "platformOffer": null, "is_giftable": true, "current_gift_offer": {"__typename": "AppStoreOffer", "id": "427726621439563"}, "externalReviews": {"count": 0}, "quality_rating_aggregate": 4.1790962018298, "support_website_url": null, "quality_ratings_by_viewer": [], "reviewInfo": {"count": 1676, "orderings": [{"key": "top", "label": "最相关"}, {"key": "most_recent", "label": "从新到旧"}]}, "firstQualityRatings": {"count": 1676, "page_info": {"end_cursor": "AQHRCBRdzZUFoEMupsRnVQHUK8vh4Kmv2UT2JGELA_hw4oaOEqhfdEtdO6Ow68UV1K5W--DQM69h9ybeshOUdL1Gkw", "start_cursor": "AQHRCBRdzZUFoEMupsRnVQHUK8vh4Kmv2UT2JGELA_hw4oaOEqhfdEtdO6Ow68UV1K5W--DQM69h9ybeshOUdL1Gkw"}, "edges": [{"node": {"id": "109214241029395", "author": {"id": "104468568170629", "display_name": "IcyOllogy", "profile_photo": {"uri": "https://scontent.oculuscdn.com/v/t64.5771-25/q92/c0.0.720.720a/s160x160/38974920_106899351260884_7707192768777178577_n.jpg?_nc_cat=110&ccb=2&_nc_sid=79b88e&_nc_ohc=FpPOpP23uy4AX9ct47d&_nc_ht=scontent.oculuscdn.com&tp=28&oh=6ba45d8e7cafc69001a147cdb63ffbb5&oe=6012287D"}}, "score": 4, "reviewDescription": "WOW! FIRST OFF WOW! Amazing experience LOVED IT!! But it's like an hour-long only. \n\nOk, so we will start with the pros first and then the cons.\n\nPros:\n\nAmazing graphics! I held my lightsaber up and was watching the reflection on my metal friend it's an amazing thing to see first hand! So to avoid any spoilers all I can say about combat for the pro's list is IT'S AWESOME!!\n\nCons:\n\nExcruciatingly short. It's like an hour-long with literally 3 or 4 combat scenes (one being a training tutorial) where you are locked or super glued or welded to the floor and can't move for some dumb reason. And because of this, combat feels lacking and extremely superficial, and somewhat weird. But if you ignore that fact then combat is really good all things considered. \n\nConclusion: Should you buy this?\n\nIf you are a huge star wars fan THEN YES ITS CHEAP SO WHY NOT!!! Also, the game is so short you can probably refund it once you are finished with it. If you are looking for an actual game with a story to play and can sink in some time and want a game worth your money then NO do NOT get this game would not recommend it. Personally, though I had a great time and don't regret buying it. Well, actually I regret it a little but I picked it up on sale so I console myself with that fact.", "reviewTitle": "Honest Review. Read before buying!", "review_helpful_count": 119, "review_rank_by_viewer": null, "date": 1606940754, "developerResponse": null}}]}, "can_viewer_review": false, "is_offer_region_restricted": false, "__isWithWebsitePageMeta": "Application", "website_page_meta": {"description": "Continue your journey into the heart of Darth Vader's dark fortress in Vader Immortal: A Star Wars VR Series - Episode II. With the fearsome Sith Lord as your guide, you'll perfect your lightsaber skills against terrifying new enemies, and master the Force as you discover the truth of an ancient mystery beneath the fiery surface of Mustafar. Starring Maya Rudolph, Vader Immortal is a canonical Star Wars experience created by ILMxLAB and Lucasfilm in collaboration with Oculus Studios.", "image_height": 405, "image_type": "image/jpeg", "image_url": "https://scontent.oculuscdn.com/v/t64.5771-25/q92/s720x720/38982573_2781078665258766_7567236079196045312_n.jpg?_nc_cat=1&ccb=2&_nc_sid=79b88e&_nc_ohc=neO2YbsILbAAX9cw4ey&_nc_ht=scontent.oculuscdn.com&tp=28&oh=e72fb1f394c6b06213748fc9b72796d1&oe=60132276", "image_width": 720, "og_locale": "zh_CN", "og_type": "website", "page_url": "https://www.oculus.com/experiences/quest/2223615721048141/", "site_name": "Oculus", "title": "Vader Immortal: Episode II · Oculus Quest"}, "fallback_ranking_trace": ""}}, "errors": [{"message": "Errors while executing operation \"StoreAppQuery\": At Query.viewer:Viewer.user: Field implementation threw an exception. Check your server logs for more information.", "severity": "ERROR", "path": ["viewer", "user"]}, {"message": "Errors while executing operation \"StoreAppQuery\": At Query.node:Application.current_offer:AppStoreOffer.buy_button_captions: Field implementation threw an exception. Check your server logs for more information.", "severity": "ERROR", "path": ["node", "current_offer", "buy_button_captions"]}, {"message": "Errors while executing operation \"StoreAppQuery\": At Query.node:Application.purchase_alerts: Field implementation threw an exception. Check your server logs for more information.", "severity": "ERROR", "path": ["node", "purchase_alerts"]}]}